Cargo.toml
MANIFEST.in
README.md
build.rs
pyproject.toml
python/fssnap/__init__.py
python/fssnap/gui.py
python/fssnap.egg-info/PKG-INFO
python/fssnap.egg-info/SOURCES.txt
python/fssnap.egg-info/dependency_links.txt
python/fssnap.egg-info/entry_points.txt
python/fssnap.egg-info/requires.txt
python/fssnap.egg-info/top_level.txt
rust/cli.rs
rust/db.rs
rust/lib.rs
rust/utils.rs
target/release-lto/fssnap-cli