Metadata-Version: 2.2
Name: fssnap
Version: 0.8.2
Project-URL: Homepage, https://anvilsecure.com
Requires-Python: >=3.8
Requires-Dist: pyside6
